ImobilebbsCodesmithJiaocheng/README.md
ImobilebbsCodesmithJiaocheng/__init__.py
ImobilebbsCodesmithJiaocheng/__main__.py
ImobilebbsCodesmithJiaocheng/file.epub
ImobilebbsCodesmithJiaocheng/index.html
ImobilebbsCodesmithJiaocheng/css/__init__.py
ImobilebbsCodesmithJiaocheng/css/annotations.css
ImobilebbsCodesmithJiaocheng/css/main.css
ImobilebbsCodesmithJiaocheng/css/normalize.css
ImobilebbsCodesmithJiaocheng/css/popup.css
ImobilebbsCodesmithJiaocheng/font/__init__.py
ImobilebbsCodesmithJiaocheng/font/fontello.eot
ImobilebbsCodesmithJiaocheng/font/fontello.svg
ImobilebbsCodesmithJiaocheng/font/fontello.ttf
ImobilebbsCodesmithJiaocheng/font/fontello.woff
ImobilebbsCodesmithJiaocheng/img/__init__.py
ImobilebbsCodesmithJiaocheng/img/annotator-glyph-sprite.png
ImobilebbsCodesmithJiaocheng/img/annotator-icon-sprite.png
ImobilebbsCodesmithJiaocheng/img/apple-touch-icon.png
ImobilebbsCodesmithJiaocheng/img/cancelfullscreen.png
ImobilebbsCodesmithJiaocheng/img/close.png
ImobilebbsCodesmithJiaocheng/img/fullscreen.png
ImobilebbsCodesmithJiaocheng/img/loader.gif
ImobilebbsCodesmithJiaocheng/img/menu-icon.png
ImobilebbsCodesmithJiaocheng/img/save.png
ImobilebbsCodesmithJiaocheng/img/saved.png
ImobilebbsCodesmithJiaocheng/img/settings-s.png
ImobilebbsCodesmithJiaocheng/img/settings.png
ImobilebbsCodesmithJiaocheng/img/star.png
ImobilebbsCodesmithJiaocheng/js/__init__.py
ImobilebbsCodesmithJiaocheng/js/epub.js
ImobilebbsCodesmithJiaocheng/js/epub.min.js
ImobilebbsCodesmithJiaocheng/js/epub.min.map
ImobilebbsCodesmithJiaocheng/js/hooks.min.js
ImobilebbsCodesmithJiaocheng/js/hooks.min.map
ImobilebbsCodesmithJiaocheng/js/reader.js
ImobilebbsCodesmithJiaocheng/js/reader.js.map
ImobilebbsCodesmithJiaocheng/js/reader.min.js
ImobilebbsCodesmithJiaocheng/js/reader.min.map
ImobilebbsCodesmithJiaocheng/js/hooks/__init__.py
ImobilebbsCodesmithJiaocheng/js/hooks/extensions/__init__.py
ImobilebbsCodesmithJiaocheng/js/hooks/extensions/highlight.js
imobilebbs_codesmith_jiaocheng-2024.3.2.0.dist-info/METADATA
imobilebbs_codesmith_jiaocheng-2024.3.2.0.dist-info/WHEEL
imobilebbs_codesmith_jiaocheng-2024.3.2.0.dist-info/entry_points.txt
imobilebbs_codesmith_jiaocheng-2024.3.2.0.dist-info/top_level.txt
imobilebbs_codesmith_jiaocheng-2024.3.2.0.dist-info/RECORD
